AUTHORS.rst
CONTRIBUTING.rst
HISTORY.rst
LICENSE
MANIFEST.in
README.rst
setup.cfg
setup.py
docs/Makefile
docs/authors.rst
docs/conf.py
docs/contributing.rst
docs/history.rst
docs/index.rst
docs/installation.rst
docs/make.bat
docs/readme.rst
docs/usage.rst
get_video_length/__init__.py
get_video_length/get_video_length.py
get_video_length.egg-info/PKG-INFO
get_video_length.egg-info/SOURCES.txt
get_video_length.egg-info/dependency_links.txt
get_video_length.egg-info/not-zip-safe
get_video_length.egg-info/top_level.txt
tests/__init__.py
tests/test_get_video_length.py