Metadata-Version: 2.1
Name: get-video-length
Version: 0.1.0
Summary: get_video_length gets the length of a video
Home-page: https://github.com/Tr4shL0rd/get_video_length
Author: Tr4shL0rd
Author-email: ketil04@gmail.com
License: MIT license
Keywords: get_video_length
Platform: UNKNOWN
Classifier: Development Status :: 2 - Pre-Alpha
Classifier: Intended Audience :: Developers
Classifier: License :: OSI Approved :: MIT License
Classifier: Natural Language :: English
Classifier: Programming Language :: Python :: 3
Classifier: Programming Language :: Python :: 3.6
Classifier: Programming Language :: Python :: 3.7
Classifier: Programming Language :: Python :: 3.8
Requires-Python: >=3.6
License-File: LICENSE
License-File: AUTHORS.rst
